tests/__init__.py
tests/test_extract.py
tests/test_extract_init.py
tests/resources/__init__.py
tests/resources/empty.py
version_extractor/__init__.py
version_extractor/extractor.py
bernardomg.version_extractor-1.1.0.dist-info/LICENSE
bernardomg.version_extractor-1.1.0.dist-info/METADATA
bernardomg.version_extractor-1.1.0.dist-info/WHEEL
bernardomg.version_extractor-1.1.0.dist-info/top_level.txt
bernardomg.version_extractor-1.1.0.dist-info/RECORD
