Metadata-Version: 2.1
Name: bernardomg.version-extractor
Version: 1.1.0
Summary: Extracts the version from a Python file
Home-page: https://github.com/Bernardo-MG/python-version-extractor
Author: Bernardo Martínez Garrido
Author-email: programming@bernardomg.com
License: MIT
Download-URL: https://pypi.python.org/pypi/version_extractor
Platform: any
Classifier: Development Status :: 5 - Production/Stable
Classifier: License :: OSI Approved :: MIT License
Classifier: Programming Language :: Python
Classifier: Programming Language :: Python :: 3
Classifier: Programming Language :: Python :: 3.6
Classifier: Programming Language :: Python :: 3.7
Classifier: Programming Language :: Python :: 3.8
Classifier: Programming Language :: Python :: 3.9
Provides-Extra: test
Requires-Dist: tox ; extra == 'test'
